rolo/__init__.py
rolo/asgi.py
rolo/client.py
rolo/dispatcher.py
rolo/proxy.py
rolo/py.typed
rolo/request.py
rolo/resource.py
rolo/response.py
rolo/router.py
rolo/gateway/__init__.py
rolo/gateway/asgi.py
rolo/gateway/chain.py
rolo/gateway/gateway.py
rolo/gateway/handlers.py
rolo/gateway/wsgi.py
rolo/routing/__init__.py
rolo/routing/converter.py
rolo/routing/handler.py
rolo/routing/pydantic.py
rolo/routing/resource.py
rolo/routing/router.py
rolo/routing/rules.py
rolo/serving/__init__.py
rolo/serving/twisted.py
rolo/testing/__init__.py
rolo/testing/pytest.py
rolo/websocket/__init__.py
rolo/websocket/adapter.py
rolo/websocket/errors.py
rolo/websocket/request.py
rolo/websocket/websocket.py
rolo-0.7.6.dist-info/licenses/LICENSE
rolo-0.7.6.dist-info/METADATA
rolo-0.7.6.dist-info/WHEEL
rolo-0.7.6.dist-info/top_level.txt
rolo-0.7.6.dist-info/RECORD
