Metadata-Version: 2.4
Name: rolo
Version: 0.7.6
Summary: A Python framework for building HTTP-based server applications
Author-email: LocalStack Contributors <info@localstack.cloud>
License: 
Classifier: Development Status :: 5 - Production/Stable
Classifier: License :: OSI Approved :: Apache Software License
Classifier: Operating System :: OS Independent
Classifier: Programming Language :: Python :: 3
Classifier: Programming Language :: Python :: 3.10
Classifier: Programming Language :: Python :: 3.11
Classifier: Programming Language :: Python :: 3.12
Classifier: Topic :: Software Development :: Libraries
Requires-Python: >=3.10
License-File: LICENSE
Requires-Dist: requests>=2.20
Requires-Dist: werkzeug>=3.0
Provides-Extra: dev
Requires-Dist: black==23.10.0; extra == "dev"
Requires-Dist: pytest>=7.0; extra == "dev"
Requires-Dist: hypercorn; extra == "dev"
Requires-Dist: pydantic; extra == "dev"
Requires-Dist: pytest_httpserver; extra == "dev"
Requires-Dist: websocket-client>=1.7.0; extra == "dev"
Requires-Dist: coverage[toml]>=5.0.0; extra == "dev"
Requires-Dist: coveralls>=3.3; extra == "dev"
Requires-Dist: localstack-twisted; extra == "dev"
Requires-Dist: ruff==0.1.0; extra == "dev"
Provides-Extra: docs
Requires-Dist: sphinx; extra == "docs"
Requires-Dist: furo; extra == "docs"
Requires-Dist: myst_parser; extra == "docs"
Dynamic: license-file
